Lshengpackage/__init__.py
Lshengpackage/network/__init__.py
Lshengpackage/network/ceshi.py
Lshengpackage/network/scan.py
Lshengpackage/simulate/__init__.py
Lshengpackage/simulate/mock_findFr.py
Lshengpackage/simulate/mock_findPic.py
Lshengpackage/simulate/__pycache__/__init__.cpython-39.pyc
Lshengpackage/simulate/__pycache__/mock_findFr.cpython-39.pyc
Lshengpackage/simulate/__pycache__/mock_findPic.cpython-39.pyc
Lshengpackage/simulate/adb/Command_adb.py
Lshengpackage/simulate/adb/__init__.py
Lshengpackage/simulate/adb/re_Pic.py
Lshengpackage/simulate/adb/__pycache__/Command_adb.cpython-39.pyc
Lshengpackage/simulate/adb/__pycache__/__init__.cpython-39.pyc
Lshengpackage/simulate/adb/__pycache__/re_Pic.cpython-39.pyc
Lshengpackage/simulate/adb/dingtalk/__init__.py
Lshengpackage/simulate/adb/dingtalk/dingtalk_api.py
Lshengpackage/simulate/adb/dingtalk/__pycache__/__init__.cpython-39.pyc
Lshengpackage/simulate/adb/dingtalk/__pycache__/dingtalk_api.cpython-39.pyc
Lshengpackage/simulate/dm/Pac_dm.py
Lshengpackage/simulate/dm/Reg.py
Lshengpackage/simulate/dm/Win_dm.py
Lshengpackage/simulate/dm/__init__.py
Lshengpackage/simulate/dm/__pycache__/Pac_dm.cpython-39.pyc
Lshengpackage/simulate/dm/__pycache__/Reg.cpython-39.pyc
Lshengpackage/simulate/dm/__pycache__/Win_dm.cpython-39.pyc
Lshengpackage/simulate/dm/__pycache__/__init__.cpython-39.pyc
Lshengpackage/tools/ChaoJiYing.py
Lshengpackage/tools/General.py
Lshengpackage/tools/Loading.py
Lshengpackage/tools/OperateFile.py
Lshengpackage/tools/SearchFile.py
Lshengpackage/tools/__init__.py
Lshengpackage/tools/__pycache__/ChaoJiYing.cpython-39.pyc
Lshengpackage/tools/__pycache__/General.cpython-39.pyc
Lshengpackage/tools/__pycache__/Loading.cpython-39.pyc
Lshengpackage/tools/__pycache__/OperateFile.cpython-39.pyc
Lshengpackage/tools/__pycache__/SearchFile.cpython-39.pyc
Lshengpackage/tools/__pycache__/__init__.cpython-39.pyc
Lshengpackage-0.4.8.dist-info/LICENSE
Lshengpackage-0.4.8.dist-info/License.md
Lshengpackage-0.4.8.dist-info/METADATA
Lshengpackage-0.4.8.dist-info/WHEEL
Lshengpackage-0.4.8.dist-info/top_level.txt
Lshengpackage-0.4.8.dist-info/RECORD
